<?xml version = '1.0' encoding = 'UTF-8'?>
<FKIndexAssociation class="oracle.dbtools.crest.model.design.relational.FKIndexAssociation" directorySegmentName="seg_0" id="1690FDD1-3ED0-E20A-2856-8A1466668F95" containerWithKeyObject="6F304829-1875-BA9B-5212-C1AEA33B0495" localFKIndex="D4911668-F642-94A9-9F95-89F8A07A7C64" name="TBL_LIKES_TB_OYENTES_FK">
<createdBy>ferna</createdBy>
<createdTime>2023-11-21 05:03:48 UTC</createdTime>
<ownerDesignName>Modelo_relacionalSCIII</ownerDesignName>
<referredTableLongName>TBL_OYENTES</referredTableLongName>
<deleteRule>NO ACTION</deleteRule>
<referredTableID>846CA1E3-4E08-F35F-D74B-6B56908B1924</referredTableID>
<keyObject>AC942334-5C38-7ACF-35EF-72A4DEBA4B50</keyObject>
<referredKeyID>AC942334-5C38-7ACF-35EF-72A4DEBA4B50</referredKeyID>
<mandatory>true</mandatory>
<refColNames>ID_OYENTE</refColNames>
<transferable>true</transferable>
<rely>false</rely>
<columnDependencyConstraintGenerateInDDL>true</columnDependencyConstraintGenerateInDDL>
</FKIndexAssociation>