<?xml version = '1.0' encoding = 'UTF-8'?>
<FKIndexAssociation class="oracle.dbtools.crest.model.design.relational.FKIndexAssociation" directorySegmentName="seg_0" id="50CC00D8-5BC2-8531-7D49-3C4156E0829D" containerWithKeyObject="87D9FA5B-E1F4-6023-39DD-71053E7B6ED1" localFKIndex="EA501F60-7B45-A096-7DEA-E4D2ADB50F8A" name="TBL_LET_CAN_TBL_IDIOM_FK">
<createdBy>ferna</createdBy>
<createdTime>2023-12-07 22:28:32 UTC</createdTime>
<ownerDesignName>Modelo_relacionalSCIII</ownerDesignName>
<referredTableLongName>TBL_IDIOMAS</referredTableLongName>
<deleteRule>NO ACTION</deleteRule>
<referredTableID>2ADADD3D-534B-1E2F-F07D-6763BAF10598</referredTableID>
<keyObject>00D1981C-60F9-C0EA-CD34-B54DF310D6CA</keyObject>
<referredKeyID>00D1981C-60F9-C0EA-CD34-B54DF310D6CA</referredKeyID>
<mandatory>true</mandatory>
<refColNames>ID_IDIOMA</refColNames>
<transferable>true</transferable>
<rely>false</rely>
<columnDependencyConstraintGenerateInDDL>true</columnDependencyConstraintGenerateInDDL>
</FKIndexAssociation>